Workbook

Sheet はじめに
B2: 資産ダッシュボード 入力シート
B4: 使い方は3ステップ
B5: 1. 下のタブ（基本情報・不動産・有価証券・預貯金・その他の借入）を順に埋めます。
B6: 2. 「ファイル → 名前を変えて保存」で my-assets.xlsx として保存します（この白紙のひな形は残しておきます）。
B7: 3. このファイルを Claude とのチャットに送ります。my-assets.json に変換してお返しします。
B9: セルの色の意味
C10: 薄い黄色 ＝ あなたが入れる欄（文字は青）
C11: 薄い灰色 ＝ Excel が自動で計算する欄（さわらないでください）
B12: （例） | C12: 灰色の斜体 ＝ 書き方の見本。消しても残しても構いません（変換のとき読み飛ばします）
B14: 入力するときの決まり
B15: ・金額は「円」で入れます。1万円は 10000 です。カンマ（,）は自分で打たなくて構いません。
B16: ・「月」と書いてある欄は 1か月分の金額です。固定資産税だけは年額を入れてください（月額は自動で計算します）。
B17: ・数字は半角で入れます。全角の１２３は使えません。
B18: ・持っていない項目は 0 のままにします。行ごと消す必要はありません。
B19: ・行が足りなくなったら、一番下の行をコピーして貼り付けて増やしてください。
B21: 気をつけていただきたいこと
B22: このファイルには氏名と資産の全額が入ります。メールやクラウドに置いたままにせず、Mac の中で保管してください。
B23: GitHub には上げません（data/ フォルダは白紙のひな形と説明書以外が除外してあります）。
B25: 「検算」タブに合計と、つじつまの合わない箇所の警告が出ます。送る前に一度ご覧ください。

Sheet 基本情報
A1: 基本情報
A3: 項目 | B3: 入力 | C3: 説明
A4: 氏名 | B4: 山田 太郎 | C4: 画面の左上に出ます
A5: 基準日 | B5: 2026-09-01 | C5: いつ時点の数字か。2026-09-01 の形で入れます
A7: 為替レート
A8: 外貨を持っている場合だけ入れます。「その日のレート」を手で固定します（自動では取りません）。
A9: 通貨 | B9: 1単位あたりの円 | C9: 説明
A10: JPY | B10: 1 | C10: 日本円。1 のまま変えないでください
A11: USD | B11: 155.2 | C11: 米ドル。1ドルが何円か
C12: 他の通貨があれば（例: EUR）

Sheet 不動産
A1: 不動産 （1行に1つの物件）
A2: 灰色の「総投資額」「累計返済額」「固定資産税(月)」「月次収支」は自動で計算されます。
A4: 物件名 | B4: 住所 | C4: 広さ(㎡) | D4: 階数 | E4: 築年数 | F4: 自己資金 | G4: 当初借入額 | H4: 残債 | I4: 借入先 | J4: 金利(年%) | K4: 借入期間(当初) 年 | L4: 借入期間(当初) か月 | M4: 毎月の返済額 | N4: 家賃収入(月) | O4: 管理費(月) | P4: 修繕積立金(月) | Q4: 固定資産税(年額) | R4: 時価 (任意) | S4: 評価日 (任意) | T4: 評価の根拠 (任意) | U4: 総投資額 | V4: 累計返済額 | W4: 固定資産税(月) | X4: 月次収支 | Y4: 借入期間 合計(か月) | Z4: 含み損益
A5: （例）物件A | B5: 東京都港区白金台 | C5: 45.5 | D5: 3 / 10 階 | E5: 15 | F5: 10000000 | G5: 40000000 | H5: 35500000 | I5: A銀行 | J5: 1.8 | K5: 26 | L5: 11 | M5: 128000 | N5: 180000 | O5: 12000 | P5: 8000 | Q5: 108000 | R5: 58000000 | S5: 2026-08-01 | T5: 不動産会社の査定書 | U5: =F5+G5 -> 50000000 | V5: =G5-H5 -> 4500000 | W5: =ROUND(Q5/12,0) -> 9000 | X5: =N5-M5-O5-P5-W5 -> 23000 | Y5: =K5*12+L5 -> 323 | Z5: =IF(R5="","",R5-U5) -> 8000000
U6: =F6+G6 -> 0 | V6: =G6-H6 -> 0 | W6: =ROUND(Q6/12,0) -> 0 | X6: =N6-M6-O6-P6-W6 -> 0 | Y6: =K6*12+L6 -> 0 | Z6: =IF(R6="","",R6-U6)
U7: =F7+G7 -> 0 | V7: =G7-H7 -> 0 | W7: =ROUND(Q7/12,0) -> 0 | X7: =N7-M7-O7-P7-W7 -> 0 | Y7: =K7*12+L7 -> 0 | Z7: =IF(R7="","",R7-U7)
U8: =F8+G8 -> 0 | V8: =G8-H8 -> 0 | W8: =ROUND(Q8/12,0) -> 0 | X8: =N8-M8-O8-P8-W8 -> 0 | Y8: =K8*12+L8 -> 0 | Z8: =IF(R8="","",R8-U8)
U9: =F9+G9 -> 0 | V9: =G9-H9 -> 0 | W9: =ROUND(Q9/12,0) -> 0 | X9: =N9-M9-O9-P9-W9 -> 0 | Y9: =K9*12+L9 -> 0 | Z9: =IF(R9="","",R9-U9)
U10: =F10+G10 -> 0 | V10: =G10-H10 -> 0 | W10: =ROUND(Q10/12,0) -> 0 | X10: =N10-M10-O10-P10-W10 -> 0 | Y10: =K10*12+L10 -> 0 | Z10: =IF(R10="","",R10-U10)
U11: =F11+G11 -> 0 | V11: =G11-H11 -> 0 | W11: =ROUND(Q11/12,0) -> 0 | X11: =N11-M11-O11-P11-W11 -> 0 | Y11: =K11*12+L11 -> 0 | Z11: =IF(R11="","",R11-U11)
U12: =F12+G12 -> 0 | V12: =G12-H12 -> 0 | W12: =ROUND(Q12/12,0) -> 0 | X12: =N12-M12-O12-P12-W12 -> 0 | Y12: =K12*12+L12 -> 0 | Z12: =IF(R12="","",R12-U12)
U13: =F13+G13 -> 0 | V13: =G13-H13 -> 0 | W13: =ROUND(Q13/12,0) -> 0 | X13: =N13-M13-O13-P13-W13 -> 0 | Y13: =K13*12+L13 -> 0 | Z13: =IF(R13="","",R13-U13)
U14: =F14+G14 -> 0 | V14: =G14-H14 -> 0 | W14: =ROUND(Q14/12,0) -> 0 | X14: =N14-M14-O14-P14-W14 -> 0 | Y14: =K14*12+L14 -> 0 | Z14: =IF(R14="","",R14-U14)
A16: ※ 行が足りないときは、最終行（14行目）をコピーして下に貼り付けてください。数式も一緒に増えます。

Sheet 有価証券
A1: 有価証券 （国内・海外 × 4種類 ＝ 8行で固定）
A2: 持っていない種類は 0 のままにします（行は消しません。入れ忘れに気づけるようにするためです）。
A3: 「その他」は暗号資産・金・銀などをまとめる欄です。金額はその通貨のままで入れます（円換算は自動）。
A5: 地域 | B5: 種類 | C5: 通貨 | D5: 取得原価 | E5: 評価額 | F5: 補足（任意） | G5: 含み損益 | H5: 円換算した評価額 | I5: 円換算した取得原価
A6: 国内 | B6: 株 | C6: JPY | D6: 2000000 | E6: 5000000 | G6: =E6-D6 -> 3000000 | H6: =ROUND(E6*IFERROR(INDEX(基本情報!$B$10:$B$13,MATCH(C6,基本情報!$A$10:$A$13,0)),0),0) -> 5000000 | I6: =ROUND(D6*IFERROR(INDEX(基本情報!$B$10:$B$13,MATCH(C6,基本情報!$A$10:$A$13,0)),0),0) -> 2000000
A7: 国内 | B7: 債券 | C7: JPY | D7: 2700000 | E7: 2500000 | G7: =E7-D7 -> -200000 | H7: =ROUND(E7*IFERROR(INDEX(基本情報!$B$10:$B$13,MATCH(C7,基本情報!$A$10:$A$13,0)),0),0) -> 2500000 | I7: =ROUND(D7*IFERROR(INDEX(基本情報!$B$10:$B$13,MATCH(C7,基本情報!$A$10:$A$13,0)),0),0) -> 2700000
A8: 国内 | B8: 投資信託 | C8: JPY | D8: 1300000 | E8: 1500000 | G8: =E8-D8 -> 200000 | H8: =ROUND(E8*IFERROR(INDEX(基本情報!$B$10:$B$13,MATCH(C8,基本情報!$A$10:$A$13,0)),0),0) -> 1500000 | I8: =ROUND(D8*IFERROR(INDEX(基本情報!$B$10:$B$13,MATCH(C8,基本情報!$A$10:$A$13,0)),0),0) -> 1300000
A9: 国内 | B9: その他 | C9: JPY | D9: 800000 | E9: 1200000 | F9: 金地金 | G9: =E9-D9 -> 400000 | H9: =ROUND(E9*IFERROR(INDEX(基本情報!$B$10:$B$13,MATCH(C9,基本情報!$A$10:$A$13,0)),0),0) -> 1200000 | I9: =ROUND(D9*IFERROR(INDEX(基本情報!$B$10:$B$13,MATCH(C9,基本情報!$A$10:$A$13,0)),0),0) -> 800000
A10: 海外 | B10: 株 | C10: USD | D10: 20000 | E10: 32000 | G10: =E10-D10 -> 12000 | H10: =ROUND(E10*IFERROR(INDEX(基本情報!$B$10:$B$13,MATCH(C10,基本情報!$A$10:$A$13,0)),0),0) -> 4966400 | I10: =ROUND(D10*IFERROR(INDEX(基本情報!$B$10:$B$13,MATCH(C10,基本情報!$A$10:$A$13,0)),0),0) -> 3104000
A11: 海外 | B11: 債券 | C11: USD | D11: 18000 | E11: 16000 | G11: =E11-D11 -> -2000 | H11: =ROUND(E11*IFERROR(INDEX(基本情報!$B$10:$B$13,MATCH(C11,基本情報!$A$10:$A$13,0)),0),0) -> 2483200 | I11: =ROUND(D11*IFERROR(INDEX(基本情報!$B$10:$B$13,MATCH(C11,基本情報!$A$10:$A$13,0)),0),0) -> 2793600
A12: 海外 | B12: 投資信託 | C12: USD | D12: 8000 | E12: 9500 | G12: =E12-D12 -> 1500 | H12: =ROUND(E12*IFERROR(INDEX(基本情報!$B$10:$B$13,MATCH(C12,基本情報!$A$10:$A$13,0)),0),0) -> 1474400 | I12: =ROUND(D12*IFERROR(INDEX(基本情報!$B$10:$B$13,MATCH(C12,基本情報!$A$10:$A$13,0)),0),0) -> 1241600
A13: 海外 | B13: その他 | C13: USD | D13: 5000 | E13: 11000 | F13: 暗号資産 | G13: =E13-D13 -> 6000 | H13: =ROUND(E13*IFERROR(INDEX(基本情報!$B$10:$B$13,MATCH(C13,基本情報!$A$10:$A$13,0)),0),0) -> 1707200 | I13: =ROUND(D13*IFERROR(INDEX(基本情報!$B$10:$B$13,MATCH(C13,基本情報!$A$10:$A$13,0)),0),0) -> 776000
A14: 合計 | D14: =SUM(D6:D13) -> 6851000 | E14: =SUM(E6:E13) -> 10268500 | F14: ※ 通貨が違うので、この行の取得原価と評価額の合計は目安です） | G14: =SUM(G6:G13) -> 3417500 | H14: =SUM(H6:H13) -> 20831200 | I14: =SUM(I6:I13) -> 14715200

Sheet 保険
A1: 保険 （1行に1つの契約）
A2: 貯蓄性のある保険（終身・養老・個人年金など）を書きます。掛け捨ての医療保険などは書きません。
A3: 評価額には「解約返戻金」（今解約したら戻る額）を入れます。毎年届く「ご契約内容のお知らせ」か保険会社のマイページで分かります。
A4: ※ 死亡保険金額は参考です。今使えるお金ではないので、資産の合計には足しません。
A6: 保険名 | B6: 保険会社 | C6: 通貨 | D6: 払込保険料 累計 | E6: 解約返戻金 | F6: 死亡保険金額 (参考・資産に含めず) | G6: 評価日 | H6: 補足（任意） | I6: 含み損益 | J6: 円換算した解約返戻金 | K6: 円換算した払込保険料
A7: （例）変額終身保険 | B7: ○○生命 | C7: JPY | D7: 3000000 | E7: 2600000 | F7: 10000000 | G7: 2026-03-31 | H7: 解約返戻金は年1回の通知の数字 | I7: =IF(A7="","",E7-D7) -> -400000 | J7: =IF(A7="","",ROUND(E7*IFERROR(INDEX(基本情報!$B$10:$B$13,MATCH(C7,基本情報!$A$10:$A$13,0)),0),0)) -> 2600000 | K7: =IF(A7="","",ROUND(D7*IFERROR(INDEX(基本情報!$B$10:$B$13,MATCH(C7,基本情報!$A$10:$A$13,0)),0),0)) -> 3000000
I8: =IF(A8="","",E8-D8) | J8: =IF(A8="","",ROUND(E8*IFERROR(INDEX(基本情報!$B$10:$B$13,MATCH(C8,基本情報!$A$10:$A$13,0)),0),0)) | K8: =IF(A8="","",ROUND(D8*IFERROR(INDEX(基本情報!$B$10:$B$13,MATCH(C8,基本情報!$A$10:$A$13,0)),0),0))
I9: =IF(A9="","",E9-D9) | J9: =IF(A9="","",ROUND(E9*IFERROR(INDEX(基本情報!$B$10:$B$13,MATCH(C9,基本情報!$A$10:$A$13,0)),0),0)) | K9: =IF(A9="","",ROUND(D9*IFERROR(INDEX(基本情報!$B$10:$B$13,MATCH(C9,基本情報!$A$10:$A$13,0)),0),0))
I10: =IF(A10="","",E10-D10) | J10: =IF(A10="","",ROUND(E10*IFERROR(INDEX(基本情報!$B$10:$B$13,MATCH(C10,基本情報!$A$10:$A$13,0)),0),0)) | K10: =IF(A10="","",ROUND(D10*IFERROR(INDEX(基本情報!$B$10:$B$13,MATCH(C10,基本情報!$A$10:$A$13,0)),0),0))
I11: =IF(A11="","",E11-D11) | J11: =IF(A11="","",ROUND(E11*IFERROR(INDEX(基本情報!$B$10:$B$13,MATCH(C11,基本情報!$A$10:$A$13,0)),0),0)) | K11: =IF(A11="","",ROUND(D11*IFERROR(INDEX(基本情報!$B$10:$B$13,MATCH(C11,基本情報!$A$10:$A$13,0)),0),0))
I12: =IF(A12="","",E12-D12) | J12: =IF(A12="","",ROUND(E12*IFERROR(INDEX(基本情報!$B$10:$B$13,MATCH(C12,基本情報!$A$10:$A$13,0)),0),0)) | K12: =IF(A12="","",ROUND(D12*IFERROR(INDEX(基本情報!$B$10:$B$13,MATCH(C12,基本情報!$A$10:$A$13,0)),0),0))
I13: =IF(A13="","",E13-D13) | J13: =IF(A13="","",ROUND(E13*IFERROR(INDEX(基本情報!$B$10:$B$13,MATCH(C13,基本情報!$A$10:$A$13,0)),0),0)) | K13: =IF(A13="","",ROUND(D13*IFERROR(INDEX(基本情報!$B$10:$B$13,MATCH(C13,基本情報!$A$10:$A$13,0)),0),0))
I14: =IF(A14="","",E14-D14) | J14: =IF(A14="","",ROUND(E14*IFERROR(INDEX(基本情報!$B$10:$B$13,MATCH(C14,基本情報!$A$10:$A$13,0)),0),0)) | K14: =IF(A14="","",ROUND(D14*IFERROR(INDEX(基本情報!$B$10:$B$13,MATCH(C14,基本情報!$A$10:$A$13,0)),0),0))
A15: 合計（見本行は数えません） | J15: =SUM(J8:J14) -> 0 | K15: =SUM(K8:K14) -> 0
A17: ※ 解約返戻金がまだ分からないときは、払込保険料累計と同じ額を入れ、「補足」に「解約返戻金 未確認（暫定）」と書いてください。含み損益は ±0 になります。

Sheet 預貯金
A1: 預貯金 （1行に1つの口座）
A2: 同じ銀行に複数口座があるときは、まとめて1行にしても、分けて書いても構いません。
A4: 金融機関 | B4: 通貨 | C4: 残高 | D4: 円換算した残高
A5: （例）A銀行 | B5: JPY | C5: 2000000 | D5: =IF(A5="","",ROUND(C5*IFERROR(INDEX(基本情報!$B$10:$B$13,MATCH(B5,基本情報!$A$10:$A$13,0)),0),0)) -> 2000000
D6: =IF(A6="","",ROUND(C6*IFERROR(INDEX(基本情報!$B$10:$B$13,MATCH(B6,基本情報!$A$10:$A$13,0)),0),0))
D7: =IF(A7="","",ROUND(C7*IFERROR(INDEX(基本情報!$B$10:$B$13,MATCH(B7,基本情報!$A$10:$A$13,0)),0),0))
D8: =IF(A8="","",ROUND(C8*IFERROR(INDEX(基本情報!$B$10:$B$13,MATCH(B8,基本情報!$A$10:$A$13,0)),0),0))
D9: =IF(A9="","",ROUND(C9*IFERROR(INDEX(基本情報!$B$10:$B$13,MATCH(B9,基本情報!$A$10:$A$13,0)),0),0))
D10: =IF(A10="","",ROUND(C10*IFERROR(INDEX(基本情報!$B$10:$B$13,MATCH(B10,基本情報!$A$10:$A$13,0)),0),0))
D11: =IF(A11="","",ROUND(C11*IFERROR(INDEX(基本情報!$B$10:$B$13,MATCH(B11,基本情報!$A$10:$A$13,0)),0),0))
D12: =IF(A12="","",ROUND(C12*IFERROR(INDEX(基本情報!$B$10:$B$13,MATCH(B12,基本情報!$A$10:$A$13,0)),0),0))
D13: =IF(A13="","",ROUND(C13*IFERROR(INDEX(基本情報!$B$10:$B$13,MATCH(B13,基本情報!$A$10:$A$13,0)),0),0))
D14: =IF(A14="","",ROUND(C14*IFERROR(INDEX(基本情報!$B$10:$B$13,MATCH(B14,基本情報!$A$10:$A$13,0)),0),0))
D15: =IF(A15="","",ROUND(C15*IFERROR(INDEX(基本情報!$B$10:$B$13,MATCH(B15,基本情報!$A$10:$A$13,0)),0),0))
D16: =IF(A16="","",ROUND(C16*IFERROR(INDEX(基本情報!$B$10:$B$13,MATCH(B16,基本情報!$A$10:$A$13,0)),0),0))
D17: =IF(A17="","",ROUND(C17*IFERROR(INDEX(基本情報!$B$10:$B$13,MATCH(B17,基本情報!$A$10:$A$13,0)),0),0))
... D19: =IF(A19="","",ROUND(C19*IFERROR(INDEX(基本情報!$B$10:$B$13,MATCH(B19,基本情報!$A$10:$A$13,0)),0),0))
A20: 合計（見本行は数えません） | D20: =SUM(D6:D19) -> 0

Sheet その他の借入
A1: 不動産以外の借入 （1行に1つのローン）
A2: 車のローン、教育ローン、多目的ローンなど。不動産のローンは「不動産」タブに書くので、ここには書きません。
A3: 借入がなければ、すべて空のままで構いません。
A5: 借入の名前 | B5: 種類 | C5: 借入先 | D5: 当初借入額 | E5: 残債 | F5: 金利(年%) | G5: 毎月の返済額 | H5: 返済済み
A6: （例）自動車ローン | B6: 車 | C6: D銀行 | D6: 3000000 | E6: 1800000 | F6: 2.5 | G6: 45000 | H6: =IF(A6="","",D6-E6) -> 1200000
H7: =IF(A7="","",D7-E7)
H8: =IF(A8="","",D8-E8)
H9: =IF(A9="","",D9-E9)
H10: =IF(A10="","",D10-E10)
H11: =IF(A11="","",D11-E11)
H12: =IF(A12="","",D12-E12)
H13: =IF(A13="","",D13-E13)
H14: =IF(A14="","",D14-E14)
H15: =IF(A15="","",D15-E15)

Sheet 検算
A1: 検算 （自動計算。送る前にここを見てください）
A2: この表はすべて自動です。画面に出る数字と同じものを先に確かめられます。
A4: 金融資産
A5: 有価証券（評価額・円） | B5: =有価証券!H14 -> 20831200 | C5: 円換算した評価額の合計
A6: うち含み損益 | B6: =有価証券!H14-有価証券!I14 -> 6116000 | C6: 円換算した評価額 − 円換算した取得原価
A7: 保険（解約返戻金・円） | B7: =保険!J15 -> 0 | C7: 死亡保険金額は含めません
A8: うち含み損益 | B8: =保険!J15-保険!K15 -> 0 | C8: 解約返戻金 − 払込保険料（保障の対価を含む）
A9: 預貯金 | B9: =預貯金!D20 -> 0 | C9: 円換算した残高の合計
A10: 金融資産合計 | B10: =有価証券!H14+保険!J15+預貯金!D20 -> 20831200 | C10: 有価証券 ＋ 保険 ＋ 預貯金（不動産は含めません）
A11: うち含み損益 | B11: =有価証券!H14+保険!J15-有価証券!I14-保険!K15 -> 6116000 | C11: 画面のサマリーに出る数字
A13: 不動産
A14: 総投資額 | B14: =SUM(不動産!$U$6:$U$14) -> 0 | C14: 自己資金 ＋ 当初借入額
A15: 自己資金累計 | B15: =SUM(不動産!$F$6:$F$14) -> 0
A16: 借入総額 | B16: =SUM(不動産!$G$6:$G$14) -> 0 | C16: 当初の借入額の合計
A17: 残債合計 | B17: =SUM(不動産!$H$6:$H$14) -> 0
A18: 累計返済額 | B18: =SUM(不動産!$V$6:$V$14) -> 0 | C18: 借入総額 − 残債合計
A19: 返済進捗率 | B19: =IFERROR(SUM(不動産!$V$6:$V$14)/SUM(不動産!$G$6:$G$14),0) -> 0 | C19: 累計返済額 ÷ 借入総額
A20: 月次収支の合計 | B20: =SUM(不動産!$X$6:$X$14) -> 0 | C20: 家賃 − 返済 − 経費。マイナスなら持ち出しです
A21: 時価合計 | B21: =IF(COUNT(不動産!$R$6:$R$14)=0,0,SUM(不動産!$R$6:$R$14)) -> 0 | C21: 手で入れた推定値。空欄の物件は数えません
A22: うち含み損益 | B22: =IF(COUNT(不動産!$R$6:$R$14)=0,0,SUM(不動産!$Z$6:$Z$14)) -> 0 | C22: 時価 − 総投資額（時価を入れた物件だけ）
A23: LTV | B23: =IFERROR(SUM(不動産!$H$6:$H$14)/SUM(不動産!$R$6:$R$14),0) -> 0 | C23: 残債合計 ÷ 時価合計
A25: 負債
A26: 不動産ローン 残債 | B26: =SUM(不動産!$H$6:$H$14) -> 0
A27: その他の借入 残債 | B27: =SUM(その他の借入!E7:E15) -> 0 | C27: 車・多目的など
A28: 総負債 | B28: =SUM(不動産!$H$6:$H$14)+SUM(その他の借入!E7:E15) -> 0 | C28: 不動産 ＋ その他
A30: 総資産・純資産
A31: 時価を入れた物件数 | B31: =COUNT(不動産!$R$6:$R$14)&" / "&COUNTA(不動産!$A$6:$A$14)&" 物件" -> 0 / 0 物件 | C31: ここが揃うと下の2つが出ます
A32: 総資産 | B32: =IF(COUNT(不動産!$R$6:$R$14)<>COUNTA(不動産!$A$6:$A$14),"時価未入力あり",有価証券!H14+保険!J15+預貯金!D20+SUM(不動産!$R$6:$R$14)) -> 20831200 | C32: 金融資産 ＋ 不動産（時価）
A33: 純資産 | B33: =IF(COUNT(不動産!$R$6:$R$14)<>COUNTA(不動産!$A$6:$A$14),"時価未入力あり",有価証券!H14+保険!J15+預貯金!D20+SUM(不動産!$R$6:$R$14)-(SUM(不動産!$H$6:$H$14)+SUM(その他の借入!E7:E15))) -> 20831200 | C33: 総資産 − 総負債
A36: つじつまの確認
A37: 「要確認」が出たら、その行の説明どおりに直してください。
A38: 残債が当初借入額より大きい物件 | B38: =IF(SUMPRODUCT((不動産!A6:A14<>"")*(不動産!H6:H14>不動産!G6:G14))>0,"要確認","OK") -> OK | C38: 残債は当初借入額以下になるはずです
A39: 残債が当初借入額より大きい借入 | B39: =IF(SUMPRODUCT((その他の借入!A7:A15<>"")*(その他の借入!E7:E15>その他の借入!D7:D15))>0,"要確認","OK") -> OK | C39: 同上
A40: マイナスの金額が入っている | B40: =IF(SUMPRODUCT((不動産!F6:H14<0)*1)+SUMPRODUCT((有価証券!D6:E13<0)*1)>0,"要確認","OK") -> OK | C40: 金額はすべて 0 以上で入れます
A41: 為替レートの無い通貨がある | B41: =IF(SUMPRODUCT(ISERROR(MATCH(有価証券!C6:C13,基本情報!$A$10:$A$13,0))*1)>0,"要確認","OK") -> OK | C41: 「基本情報」タブの為替レートに、使った通貨を足してください
A42: 氏名と基準日が入っている | B42: =IF(OR(基本情報!B4="",基本情報!B5=""),"要確認","OK") -> OK | C42: どちらも必須です
A43: 借入期間の「か月」が0〜11か | B43: =IF(SUMPRODUCT((不動産!A6:A14<>"")*((不動産!L6:L14<0)+(不動産!L6:L14>11)))>0,"要確認","OK") -> OK | C43: 12か月以上は「年」の側に繰り上げてください
A44: 保険にレートの無い通貨がある | B44: =IF(SUMPRODUCT((保険!A8:A14<>"")*ISERROR(MATCH(保険!C8:C14,基本情報!$A$10:$A$13,0)))>0,"要確認","OK") -> OK | C44: 「基本情報」タブの為替レートに、使った通貨を足してください
